av_video/__init__.py
av_video/video.py
av_video-0.0.1.dist-info/METADATA
av_video-0.0.1.dist-info/WHEEL
av_video-0.0.1.dist-info/licenses/LICENSE
av_video-0.0.1.dist-info/RECORD
