Metadata-Version: 2.4
Name: av-video
Version: 0.0.1
Summary: Convert videos to image frames and vice versa.
Project-URL: Repository, https://github.com/imyizhang/av-video
Author-email: Yi Zhang <yizhang.dev@gmail.com>
License-Expression: MIT
License-File: LICENSE
Requires-Python: >=3.10
Requires-Dist: av
Requires-Dist: pillow
Requires-Dist: tqdm
Provides-Extra: dev
Requires-Dist: ruff; extra == 'dev'
